LICENSE
README.md
setup.py
ase_db_extension/__init__.py
ase_db_extension/ext_row.py
ase_db_extension/function.py
ase_db_extension/general.py
ase_db_extension.egg-info/PKG-INFO
ase_db_extension.egg-info/SOURCES.txt
ase_db_extension.egg-info/dependency_links.txt
ase_db_extension.egg-info/requires.txt
ase_db_extension.egg-info/top_level.txt
test/test_ext_row.py
test/test_function.py