Metadata-Version: 2.1
Name: ase-db-extension
Version: 0.0.4
Summary: database for ase.db.
Home-page: https://github.com/boliqq07/perovskite
Author: wangchangxin
Author-email: 986798607@qq.com
Maintainer: wangchangxin
License: UNKNOWN
Keywords: database, structure
Platform: Windows
Platform: Unix
Classifier: Development Status :: 4 - Beta
Classifier: Intended Audience :: Science/Research
Classifier: Natural Language :: English
Classifier: Operating System :: Microsoft :: Windows
Classifier: Operating System :: Unix
Classifier: Programming Language :: Python :: 3.6
Classifier: Programming Language :: Python :: 3.7
Classifier: Programming Language :: Python :: 3.8
Classifier: Programming Language :: Python :: 3.9
Requires-Python: >=3.6
License-File: LICENSE
